tinytex/__init__.py
tinytex/atlas.py
tinytex/geometry.py
tinytex/noise.py
tinytex/resampling.py
tinytex/sdf.py
tinytex/smoothstep.py
tinytex/tiling.py
tinytex/util.py
tinytex/voronoi.py
tinytex/warping.py
tinytex/wavelet.py
tinytex/rand/__init__.py
tinytex/rand/hash.py
tinytex/rand/scramble.py
tinytex/scripts/post_install.py
tinytex/ti/__init__.py
tinytex/ti/params.py
tinytex/ti/prep.py
tinytex/ti/sampler1d.py
tinytex/ti/sampler2d.py
tinytex/ti/sampler3d.py
tinytex/ti/splines.py
tinytex/ti/texture1d.py
tinytex/ti/texture2d.py
tinytex/ti/texture3d.py
tinytex-0.2.1.dist-info/licenses/LICENSE.txt
tinytex-0.2.1.dist-info/METADATA
tinytex-0.2.1.dist-info/WHEEL
tinytex-0.2.1.dist-info/entry_points.txt
tinytex-0.2.1.dist-info/top_level.txt
tinytex-0.2.1.dist-info/RECORD
