Metadata-Version: 2.4
Name: tinytex
Version: 0.2.1
Summary: Lorem ipsum
Author-email: Sam Izdat <ghsamizdat@gmail.com>
Project-URL: Homepage, https://sam-izdat.github.io/tinytex
Project-URL: Issues, https://github.com/Sam-Izdat/tinytex/issues
Classifier: Programming Language :: Python :: 3
Classifier: License :: OSI Approved :: MIT License
Classifier: Operating System :: OS Independent
Requires-Python: >=3.8
License-File: LICENSE.txt
Requires-Dist: numpy<2.0.0,>=1.21.5
Requires-Dist: tinycio>=0.6.1
Requires-Dist: scikit-fmm~=2023.4.2
Requires-Dist: scipy~=1.13.0
Requires-Dist: toml<1.0.0,>=0.10.2
Requires-Dist: tqdm<5.0.0,>=4.66.1
Dynamic: license-file
